LLMEmbed/__init__.py
LLMEmbed/example.py
llmembed-1.0.0.dist-info/METADATA
llmembed-1.0.0.dist-info/WHEEL
llmembed-1.0.0.dist-info/top_level.txt
llmembed-1.0.0.dist-info/RECORD
