Metadata-Version: 2.4
Name: LLMEmbed
Version: 1.0.0
Summary: A python library for 
Author-email: Kailas P S <kailaspsudheer@gmail.com>
License-Expression: MIT
Classifier: Programming Language :: Python :: 3
Classifier: Operating System :: OS Independent
Requires-Python: >=3.8
Requires-Dist: numpy
